<?xml version="1.0" encoding="utf-8"?>
<!DOCTYPE hibernate-mapping PUBLIC "-//Hibernate/Hibernate Mapping DTD 3.0//EN"
"http://hibernate.sourceforge.net/hibernate-mapping-3.0.dtd">
<!-- 
    Mapping file autogenerated by MyEclipse Persistence Tools
-->
<hibernate-mapping>
    <class name="com.apps.party.entitymodel.PartyContactMech" table="party_contact_mech" catalog="ofbiztest">
        <composite-id name="id" class="com.apps.party.entitymodel.PartyContactMechId">
            <key-property name="partyId" type="java.lang.String">
                <column name="PARTY_ID" length="20" />
            </key-property>
            <key-property name="contactMechId" type="java.lang.String">
                <column name="CONTACT_MECH_ID" length="20" />
            </key-property>
            <key-property name="fromDate" type="java.util.Date">
                <column name="FROM_DATE" length="19" />
            </key-property>
        </composite-id>
        <property name="thruDate" type="java.util.Date">
            <column name="THRU_DATE" length="19" />
        </property>
        <property name="roleTypeId" type="java.lang.String">
            <column name="ROLE_TYPE_ID" length="20" />
        </property>
        <property name="allowSolicitation" type="java.lang.String">
            <column name="ALLOW_SOLICITATION" length="1" />
        </property>
        <property name="extension" type="java.lang.String">
            <column name="EXTENSION" />
        </property>
        <property name="verified" type="java.lang.String">
            <column name="VERIFIED" length="1" />
        </property>
        <property name="comments" type="java.lang.String">
            <column name="COMMENTS" />
        </property>
        <property name="yearsWithContactMech" type="java.lang.Long">
            <column name="YEARS_WITH_CONTACT_MECH" precision="20" scale="0" />
        </property>
        <property name="monthsWithContactMech" type="java.lang.Long">
            <column name="MONTHS_WITH_CONTACT_MECH" precision="20" scale="0" />
        </property>
        <property name="lastUpdatedStamp" type="java.util.Date">
            <column name="LAST_UPDATED_STAMP" length="19" />
        </property>
        <property name="lastUpdatedTxStamp" type="java.util.Date">
            <column name="LAST_UPDATED_TX_STAMP" length="19" />
        </property>
        <property name="createdStamp" type="java.util.Date">
            <column name="CREATED_STAMP" length="19" />
        </property>
        <property name="createdTxStamp" type="java.util.Date">
            <column name="CREATED_TX_STAMP" length="19" />
        </property>
    </class>
</hibernate-mapping>
